[
null,
{"id":1,"expanded":true,"name":"Rascunho","order":22,"parentId":0,"scrollX":619,"scrollY":344},
{"id":2,"expanded":true,"name":"Casa","order":3,"parentId":17,"scrollX":796.5,"scrollY":445.5},
{"id":3,"expanded":true,"name":"Meu Quarto","order":6,"parentId":5,"scrollX":796.5,"scrollY":445.5},
{"id":4,"expanded":true,"name":"Casa 1F","order":4,"parentId":2,"scrollX":796.5,"scrollY":445.5},
{"id":5,"expanded":true,"name":"Casa 2F","order":5,"parentId":2,"scrollX":634.8,"scrollY":360.59999999999997},
{"id":6,"expanded":true,"name":"Quarto Irmão","order":7,"parentId":5,"scrollX":531,"scrollY":297},
{"id":7,"expanded":false,"name":"Banheiro","order":8,"parentId":5,"scrollX":529,"scrollY":291.5},
{"id":8,"expanded":true,"name":"Casa 3F","order":9,"parentId":2,"scrollX":612,"scrollY":333.5},
{"id":9,"expanded":false,"name":"Event Spawn","order":24,"parentId":1,"scrollX":796.5,"scrollY":445.5},
{"id":10,"expanded":true,"name":"Mapa","order":1,"parentId":0,"scrollX":796.5,"scrollY":445.5},
{"id":11,"expanded":true,"name":"Cidade Rascunho","order":23,"parentId":1,"scrollX":1075.5,"scrollY":822},
{"id":12,"expanded":true,"name":"Quarto Pais","order":10,"parentId":8,"scrollX":531,"scrollY":297},
{"id":13,"expanded":true,"name":"Praia","order":11,"parentId":10,"scrollX":637.1999999999999,"scrollY":356.4},
{"id":14,"expanded":true,"name":"Faculdade entrada","order":12,"parentId":10,"scrollX":627,"scrollY":368},
{"id":15,"expanded":true,"name":"Faculdade andar 4","order":13,"parentId":14,"scrollX":619,"scrollY":352},
{"id":16,"expanded":true,"name":"sala de aula","order":15,"parentId":14,"scrollX":619,"scrollY":352},
{"id":17,"expanded":true,"name":"Cidade","order":2,"parentId":10,"scrollX":808.5,"scrollY":535.5},
{"id":18,"expanded":true,"name":"patio FAESA","order":20,"parentId":14,"scrollX":743.3333333333334,"scrollY":1037.3333333333333},
{"id":19,"expanded":false,"name":"nucleo de atendimento ao aluno","order":14,"parentId":14,"scrollX":796.5,"scrollY":457.5},
{"id":20,"expanded":false,"name":"pátio2-praça do por do sol ","order":21,"parentId":18,"scrollX":619,"scrollY":344},
{"id":21,"expanded":true,"name":"NAT entrada","order":19,"parentId":14,"scrollX":619,"scrollY":352},
{"id":22,"expanded":false,"name":"Sala NAT","order":18,"parentId":14,"scrollX":619,"scrollY":352},
{"id":23,"expanded":true,"name":"Banheiro Másculino","order":17,"parentId":14,"scrollX":619,"scrollY":352},
{"id":24,"expanded":false,"name":"Banheiro Feminino ","order":16,"parentId":14,"scrollX":619,"scrollY":352}
]